python_keepachangelog/__init__.py
python_keepachangelog/changelog.py
python_keepachangelog-0.0.2.dist-info/WHEEL
python_keepachangelog-0.0.2.dist-info/METADATA
python_keepachangelog-0.0.2.dist-info/RECORD
